send_sms/__init__.py
send_sms/admin.py
send_sms/apps.py
send_sms/models.py
send_sms/tests.py
send_sms/views.py
send_sms/migrations/0001_initial.py
send_sms/migrations/0002_remove_smssettings_static_parameters_smsparameters.py
send_sms/migrations/0003_rename_parameter_smsparameters_parameter_and_more.py
send_sms/migrations/__init__.py
django_universal_sms-1.0.6.dist-info/LICENSE.txt
django_universal_sms-1.0.6.dist-info/METADATA
django_universal_sms-1.0.6.dist-info/WHEEL
django_universal_sms-1.0.6.dist-info/top_level.txt
django_universal_sms-1.0.6.dist-info/RECORD
